LICENSE.md
MANIFEST.in
README.md
requirements.txt
setup.py
HNSCDP/HNSC.py
HNSCDP/HNSC_predict.py
HNSCDP/__init__.py
HNSCDP/label_f.py
HNSCDP/plot.py
HNSC_classifier.egg-info/PKG-INFO
HNSC_classifier.egg-info/SOURCES.txt
HNSC_classifier.egg-info/dependency_links.txt
HNSC_classifier.egg-info/entry_points.txt
HNSC_classifier.egg-info/requires.txt
HNSC_classifier.egg-info/top_level.txt