Metadata-Version: 2.1
Name: HNSC-classifier
Version: 1.0
Summary: HNSC classifier
Home-page: https://github.com/yangfangs/HNSC-classifier
Author: Yang Fang
Author-email: 506528950@qq.com
License: GNU General Public License v3.0
License-File: LICENSE.md
